jsongetter/__init__.py
jsongetter/jsongetter.py
jsongetter/node.py
jsongetter-1.0.0.dist-info/licenses/LICENSE.md
jsongetter-1.0.0.dist-info/METADATA
jsongetter-1.0.0.dist-info/WHEEL
jsongetter-1.0.0.dist-info/top_level.txt
jsongetter-1.0.0.dist-info/RECORD
